aliddns/__init__.py
aliddns/__main__.py
aliddns/config.py
aliddns/ddns.py
aliddns/record.py
aliddns/utils.py
aliddns/yunresolver.py
aliddns2/__init__.py
aliddns2/__main__.py
aliddns2/config.py
aliddns2/ddns.py
aliddns2/record.py
aliddns2/utils.py
aliddns2/yunresolver.py
aliddns2-0.1.1.dist-info/METADATA
aliddns2-0.1.1.dist-info/WHEEL
aliddns2-0.1.1.dist-info/top_level.txt
aliddns2-0.1.1.dist-info/RECORD
